LICENSE.txt
MANIFEST.in
README.txt
setup.py
django_lfc.egg-info/PKG-INFO
django_lfc.egg-info/SOURCES.txt
django_lfc.egg-info/dependency_links.txt
django_lfc.egg-info/not-zip-safe
django_lfc.egg-info/requires.txt
django_lfc.egg-info/top_level.txt
lfc/__init__.py
lfc/admin.py
lfc/context_processors.py
lfc/feeds.py
lfc/listeners.py
lfc/managers.py
lfc/models.py
lfc/settings.py
lfc/signals.py
lfc/sitemap.py
lfc/urls.py
lfc/views.py
lfc/fields/__init__.py
lfc/fields/autocomplete.py
lfc/fields/readonly.py
lfc/fields/thumbs.py
lfc/fields/wysiwyg.py
lfc/fixtures/initial.xml
lfc/fixtures/superuser.xml
lfc/locale/de/LC_MESSAGES/django.mo
lfc/locale/de/LC_MESSAGES/django.po
lfc/locale/fr/LC_MESSAGES/django.po
lfc/locale/pl/LC_MESSAGES/django.mo
lfc/locale/pl/LC_MESSAGES/django.po
lfc/manage/__init__.py
lfc/manage/forms.py
lfc/manage/urls.py
lfc/manage/views.py
lfc/management/__init__.py
lfc/management/commands/__init__.py
lfc/management/commands/lfc_init.py
lfc/management/commands/lfc_init_simple.py
lfc/management/commands/test_rt.py
lfc/management/commands/utils.py
lfc/static/.DS_Store
lfc/static/blueprint/ie.css
lfc/static/blueprint/print.css
lfc/static/blueprint/screen.css
lfc/static/blueprint/plugins/buttons/readme.txt
lfc/static/blueprint/plugins/buttons/screen.css
lfc/static/blueprint/plugins/buttons/icons/cross.png
lfc/static/blueprint/plugins/buttons/icons/key.png
lfc/static/blueprint/plugins/buttons/icons/tick.png
lfc/static/blueprint/plugins/fancy-type/readme.txt
lfc/static/blueprint/plugins/fancy-type/screen.css
lfc/static/blueprint/plugins/link-icons/readme.txt
lfc/static/blueprint/plugins/link-icons/screen.css
lfc/static/blueprint/plugins/link-icons/icons/doc.png
lfc/static/blueprint/plugins/link-icons/icons/email.png
lfc/static/blueprint/plugins/link-icons/icons/external.png
lfc/static/blueprint/plugins/link-icons/icons/feed.png
lfc/static/blueprint/plugins/link-icons/icons/im.png
lfc/static/blueprint/plugins/link-icons/icons/pdf.png
lfc/static/blueprint/plugins/link-icons/icons/visited.png
lfc/static/blueprint/plugins/link-icons/icons/xls.png
lfc/static/blueprint/plugins/rtl/readme.txt
lfc/static/blueprint/plugins/rtl/screen.css
